voice_mcp/__init__.py
voice_mcp/__main__.py
voice_mcp/__version__.py
voice_mcp/cli.py
voice_mcp/config.py
voice_mcp/core.py
voice_mcp/provider_discovery.py
voice_mcp/providers.py
voice_mcp/server.py
voice_mcp/shared.py
voice_mcp/statistics.py
voice_mcp/streaming.py
voice_mcp/prompts/README.md
voice_mcp/prompts/__init__.py
voice_mcp/prompts/conversation.py
voice_mcp/prompts/kokoro_management.py
voice_mcp/prompts/show_and_tell.py
voice_mcp/prompts/status.py
voice_mcp/prompts/voice_commands.py
voice_mcp/resources/__init__.py
voice_mcp/resources/audio_files.py
voice_mcp/resources/statistics.py
voice_mcp/tools/__init__.py
voice_mcp/tools/conversation.py
voice_mcp/tools/devices.py
voice_mcp/tools/livekit.py
voice_mcp/tools/providers.py
voice_mcp/tools/services.py
voice_mcp/tools/statistics.py
voice_mcp/tools/synthesis.py
voice_mcp/tools/transcription.py
voice_mcp/utils/__init__.py
voice_mcp/utils/event_logger.py
voice_mcp/utils/format_migration.py
voice_mcp-2.4.1.dist-info/METADATA
voice_mcp-2.4.1.dist-info/WHEEL
voice_mcp-2.4.1.dist-info/entry_points.txt
voice_mcp-2.4.1.dist-info/RECORD
