Metadata-Version: 2.4
Name: voice-mcp
Version: 2.4.1
Summary: Voice interaction capabilities for Model Context Protocol (MCP) servers
Project-URL: Homepage, https://github.com/mbailey/voicemode
Project-URL: Repository, https://github.com/mbailey/voicemode
Project-URL: Issues, https://github.com/mbailey/voicemode/issues
Author-email: mbailey <mbailey@example.com>
License: MIT
Keywords: ai,livekit,llm,mcp,speech,stt,tts,voice
Classifier: Development Status :: 4 - Beta
Classifier: Intended Audience :: Developers
Classifier: License :: OSI Approved :: MIT License
Classifier: Programming Language :: Python :: 3
Classifier: Programming Language :: Python :: 3.8
Classifier: Programming Language :: Python :: 3.9
Classifier: Programming Language :: Python :: 3.10
Classifier: Programming Language :: Python :: 3.11
Classifier: Programming Language :: Python :: 3.12
Classifier: Programming Language :: Python :: 3.13
Classifier: Topic :: Multimedia :: Sound/Audio :: Speech
Classifier: Topic :: Software Development :: Libraries
Requires-Python: >=3.10
Requires-Dist: anyio>=3.0.0
Requires-Dist: audioop-lts>=0.2.1; python_version >= '3.13'
Requires-Dist: fastmcp>=2.0.0
Requires-Dist: httpx>=0.24.0
Requires-Dist: livekit>=0.18.0
Requires-Dist: numpy
Requires-Dist: openai>=1.0.0
Requires-Dist: psutil>=5.9.0
Requires-Dist: pydub
Requires-Dist: scipy
Requires-Dist: sounddevice
Requires-Dist: uv>=0.4.0
Provides-Extra: dev
Requires-Dist: pytest-asyncio>=0.21.0; extra == 'dev'
Requires-Dist: pytest-mock>=3.10.0; extra == 'dev'
Requires-Dist: pytest>=7.0.0; extra == 'dev'
